[1,0,0,[["cc.Mesh",["_native","_dataLength","_hash","_struct"],0,11]],[[0,0,1,2,3,4]],[[0,".bin",21168,426608923,[{"primitives":[{"primitiveMode":7,"vertexBundelIndices":[0],"indexView":{"offset":15792,"length":5376,"count":1344,"stride":4}}],"vertexBundles":[{"view":{"offset":0,"length":15792,"count":329,"stride":48},"attributes":[{"name":"a_position","format":32,"isNormalized":false},{"name":"a_normal","format":32,"isNormalized":false},{"name":"a_texCoord","format":21,"isNormalized":false},{"name":"a_tangent","format":44,"isNormalized":false}]}]},"minPosition",8,[1,-0.5636530518531799,0.0302886962890625,-0.6396805047988892],"maxPosition",8,[1,0.5637664198875427,0.585220456123352,0.6333085894584656]]]],0,0,[],[],[]]
